aleph_client/__init__.py
aleph_client/__main__.py
aleph_client/account.py
aleph_client/models.py
aleph_client/utils.py
aleph_client/commands/__init__.py
aleph_client/commands/about.py
aleph_client/commands/account.py
aleph_client/commands/aggregate.py
aleph_client/commands/authorizations.py
aleph_client/commands/credit.py
aleph_client/commands/domain.py
aleph_client/commands/files.py
aleph_client/commands/help_strings.py
aleph_client/commands/message.py
aleph_client/commands/node.py
aleph_client/commands/pricing.py
aleph_client/commands/program.py
aleph_client/commands/utils.py
aleph_client/commands/instance/__init__.py
aleph_client/commands/instance/display.py
aleph_client/commands/instance/network.py
aleph_client/commands/instance/port_forwarder.py
aleph_client/commands/program_utils/runtime_checker.squashfs
aleph_client/commands/program_utils/runtime_checker/main.py
aleph_client-1.9.0.dist-info/METADATA
aleph_client-1.9.0.dist-info/WHEEL
aleph_client-1.9.0.dist-info/entry_points.txt
aleph_client-1.9.0.dist-info/licenses/AUTHORS.rst
aleph_client-1.9.0.dist-info/licenses/LICENSE.txt
aleph_client-1.9.0.dist-info/RECORD
