Metadata-Version: 2.4
Name: aleph-client
Version: 1.9.0
Summary: Python Client library for the Aleph Cloud network
Project-URL: Discussions, https://community.aleph.cloud/
Project-URL: Documentation, https://docs.aleph.cloud/devhub/sdks-and-tools/aleph-cli/
Project-URL: Issues, https://github.com/aleph-im/aleph-client/issues
Project-URL: Source, https://github.com/aleph-im/aleph-client
Author-email: Aleph Cloud Team <hello@aleph.cloud>
License: The MIT License (MIT)
License-File: AUTHORS.rst
License-File: LICENSE.txt
Keywords: Aleph Cloud,Client,Library,Python
Classifier: Development Status :: 4 - Beta
Classifier: Environment :: Console
Classifier: Framework :: aiohttp
Classifier: License :: OSI Approved :: MIT License
Classifier: Programming Language :: Python :: 3 :: Only
Classifier: Programming Language :: Python :: 3.9
Classifier: Programming Language :: Python :: 3.10
Classifier: Programming Language :: Python :: 3.11
Classifier: Programming Language :: Python :: 3.12
Classifier: Topic :: System :: Distributed Computing
Requires-Python: >=3.9
Requires-Dist: aiodns==3.1.1
Requires-Dist: aiohttp==3.11.15
Requires-Dist: aleph-message>=1.0.5
Requires-Dist: aleph-sdk-python==2.3
Requires-Dist: base58==2.1.1
Requires-Dist: click<8.2
Requires-Dist: ledgerblue>=0.1.48
Requires-Dist: ledgereth>=0.10
Requires-Dist: py-sr25519-bindings==0.2
Requires-Dist: pydantic>=2
Requires-Dist: pygments==2.19.1
Requires-Dist: pynacl==1.5
Requires-Dist: python-magic==0.4.27
Requires-Dist: rich==13.9.*
Requires-Dist: setuptools>=65.5
Requires-Dist: substrate-interface==1.7.11
Requires-Dist: textual==0.73
Requires-Dist: typer==0.15.2
Provides-Extra: cosmos
Requires-Dist: cosmospy==6; extra == 'cosmos'
Provides-Extra: docs
Requires-Dist: sphinxcontrib-plantuml==0.30; extra == 'docs'
Provides-Extra: ethereum
Requires-Dist: eth-account>=0.4; extra == 'ethereum'
Provides-Extra: nuls2
Requires-Dist: aleph-nuls2==0.1; extra == 'nuls2'
Provides-Extra: polkadot
Requires-Dist: substrate-interface==1.7.11; extra == 'polkadot'
Provides-Extra: solana
Requires-Dist: base58==2.1.1; extra == 'solana'
Requires-Dist: pynacl==1.5; extra == 'solana'
Provides-Extra: tezos
Requires-Dist: aleph-pytezos==3.13.4; extra == 'tezos'
Requires-Dist: pynacl==1.5; extra == 'tezos'
